specifypro_cli/__init__.py
specifypro-1.0.0.dist-info/METADATA
specifypro-1.0.0.dist-info/WHEEL
specifypro-1.0.0.dist-info/entry_points.txt
specifypro-1.0.0.dist-info/licenses/LICENSE
specifypro-1.0.0.dist-info/RECORD
